{
  "defaultSeverity": "error",
  "extends": [
      "tslint:recommended"
  ],
  "jsRules": {},
  "rules": {
    "class-name": true,
    "curly": false,
    "eofline": false,
    "expr" : true,
    "forin": true,
    "indent": [true, "spaces"],
    "label-position": true,
    "label-undefined": true,
    "max-line-length": [false],
    "no-arg": true,
    "no-bitwise": true,
    "no-console": [true,
      "debug",
      "info",
      "time",
      "timeEnd",
      "trace"
    ],
    "no-construct": true,
    "no-shadowed-variable": false,
    "jsdoc-format": false,
    "no-debugger": true,
    "interface-name": false,
    "prefer-const": false,
    "no-var-requires": false,
    "no-empty": false,
    "no-duplicate-key": true,
    "no-duplicate-variable": true,
    "arrow-parens": false,
    "no-eval": true,
    "no-string-literal": false,
    "no-namespace": false,
    "no-var-keyword": false,
    "only-arrow-functions": false,
    "no-switch-case-fall-through": true,
    "no-trailing-comma": false,
    "no-trailing-whitespace": false,
    "no-unused-expression": false,
    "no-unused-variable": true,
    "no-unreachable": true,
    "no-use-before-declare": true,
    "ordered-imports": false,
    "object-literal-sort-keys": false,
    "max-file-line-count": false,
    "object-literal-key-quotes": false,
    "trailing-comma": false,
    "quotemark": false,
    "one-line": [true,
      "check-open-brace",
      "check-catch",
      "check-else",
      "check-whitespace"
    ],
    "radix": false,
    "semicolon": [false],
    "triple-equals": [true, "allow-null-check"],
    "variable-name": false,
    "whitespace": [true,
      "check-branch",
      "check-decl",
      "check-operator",
      "check-separator",
      "check-type"
    ]
  },
  "rulesDirectory": []
}